piperider_cli/VERSION
piperider_cli/__init__.py
piperider_cli/__main__.py
piperider_cli/cli.py
piperider_cli/compare_report.py
piperider_cli/workspace.py
piperider_cli/assertion_engine/__init__.py
piperider_cli/assertion_engine/assertion.py
piperider_cli/data/__init__.py
piperider_cli/data/__pycache__/__init__.cpython-38.pyc
piperider_cli/data/fake/__init__.py
piperider_cli/data/fake/fake.db
piperider_cli/data/piperider-init-template/config.yml
piperider_cli/data/piperider-init-template/assertions/placeholder.txt
piperider_cli/data/piperider-init-template/plugins/customized_assertions.py
piperider_cli/data/report/comparison-report/asset-manifest.json
piperider_cli/data/report/comparison-report/index.html
piperider_cli/data/report/comparison-report/logo/android-icon-144x144.png
piperider_cli/data/report/comparison-report/logo/android-icon-192x192.png
piperider_cli/data/report/comparison-report/logo/android-icon-36x36.png
piperider_cli/data/report/comparison-report/logo/android-icon-48x48.png
piperider_cli/data/report/comparison-report/logo/android-icon-72x72.png
piperider_cli/data/report/comparison-report/logo/android-icon-96x96.png
piperider_cli/data/report/comparison-report/logo/apple-icon-114x114.png
piperider_cli/data/report/comparison-report/logo/apple-icon-120x120.png
piperider_cli/data/report/comparison-report/logo/apple-icon-144x144.png
piperider_cli/data/report/comparison-report/logo/apple-icon-152x152.png
piperider_cli/data/report/comparison-report/logo/apple-icon-180x180.png
piperider_cli/data/report/comparison-report/logo/apple-icon-57x57.png
piperider_cli/data/report/comparison-report/logo/apple-icon-60x60.png
piperider_cli/data/report/comparison-report/logo/apple-icon-72x72.png
piperider_cli/data/report/comparison-report/logo/apple-icon-76x76.png
piperider_cli/data/report/comparison-report/logo/apple-icon-precomposed.png
piperider_cli/data/report/comparison-report/logo/apple-icon.png
piperider_cli/data/report/comparison-report/logo/browserconfig.xml
piperider_cli-0.1.3.12.dist-info/LICENSE
piperider_cli-0.1.3.12.dist-info/METADATA
piperider_cli-0.1.3.12.dist-info/WHEEL
piperider_cli-0.1.3.12.dist-info/entry_points.txt
piperider_cli-0.1.3.12.dist-info/top_level.txt
piperider_cli-0.1.3.12.dist-info/RECORD
