Metadata-Version: 2.1
Name: piperider-cli
Version: 0.1.3.12
Summary: PiperRider CLI
Home-page: https://github.com/InfuseAI/piperider-cli
Author: InfuseAI Dev Team
Author-email: dev@infuseai.io
Project-URL: Bug Tracker, https://github.com/InfuseAI/piperider-cli/issues
Classifier: Programming Language :: Python :: 3
Classifier: License :: OSI Approved :: Apache Software License
Classifier: Operating System :: OS Independent
Classifier: Development Status :: 4 - Beta
Requires-Python: >=3.6
License-File: LICENSE
Requires-Dist: ruamel.yaml
Requires-Dist: sqlalchemy
Requires-Dist: sentry-sdk
Requires-Dist: rich
Requires-Dist: click
Requires-Dist: python-dateutil
Requires-Dist: inquirer
Provides-Extra: dev
Requires-Dist: pytest (>=4.6) ; extra == 'dev'
Requires-Dist: pytest-flake8 ; extra == 'dev'
Requires-Dist: flake8 (==3.9.2) ; extra == 'dev'
Requires-Dist: pytest-mypy ; extra == 'dev'
Requires-Dist: pytest-cov ; extra == 'dev'
Requires-Dist: twine ; extra == 'dev'
Provides-Extra: postgres
Requires-Dist: psycopg2-binary ; extra == 'postgres'
Provides-Extra: snowflake
Requires-Dist: snowflake-sqlalchemy ; extra == 'snowflake'
